{
  "project_info": {
    "project_number": "1076977347228",
    "firebase_url": "https://mappicker-351915-default-rtdb.asia-southeast1.firebasedatabase.app",
    "project_id": "mappicker-351915",
    "storage_bucket": "mappicker-351915.appspot.com"
  },
  "client": [
    {
      "client_info": {
        "mobilesdk_app_id": "1:1076977347228:android:d8629c7005a2697d019b59",
        "android_client_info": {
          "package_name": "com.mappicker"
        }
      },
      "oauth_client": [
        {
          "client_id": "1076977347228-j27tmp2hd05plkncdjejr3vnn7nvdprl.apps.googleusercontent.com",
          "client_type": 1,
          "android_info": {
            "package_name": "com.mappicker",
            "certificate_hash": "5e8f16062ea3cd2c4a0d547876baa6f38cabf625"
          }
        },
        {
          "client_id": "1076977347228-q46013en06r7vtu95sh6uc7lf3t8kg2j.apps.googleusercontent.com",
          "client_type": 3
        }
      ],
      "api_key": [
        {
          "current_key": "AIzaSyC2X7l_vtupP5IiRddObP6026Eu6WzvaJY"
        }
      ],
      "services": {
        "appinvite_service": {
          "other_platform_oauth_client": [
            {
              "client_id": "1076977347228-q46013en06r7vtu95sh6uc7lf3t8kg2j.apps.googleusercontent.com",
              "client_type": 3
            }
          ]
        }
      }
    }
  ],
  "configuration_version": "1"
}